{
	"format_version": "1.12.0",
	"minecraft:geometry": [
		{
			"description": {
				"identifier": "geometry.cherry_energy_arrow",
				"texture_width": 32,
				"texture_height": 32,
				"visible_bounds_width": 2,
				"visible_bounds_height": 1.5,
				"visible_bounds_offset": [0, 0.25, 0]
			},
			"bones": [
				{
					"name": "leaf",
					"pivot": [0, 0, 0]
				},
				{
					"name": "peel1",
					"parent": "leaf",
					"pivot": [-0.23367, 1.53206, -0.35],
					"cubes": [
						{
							"origin": [-0.83367, 0.03206, -0.65],
							"size": [1.1, 1, 1],
							"uv": {
								"north": {"uv": [0, 0], "uv_size": [1, 1]},
								"east": {"uv": [0, 2], "uv_size": [1, 1]},
								"south": {"uv": [2, 0], "uv_size": [1, 1]},
								"west": {"uv": [2, 2], "uv_size": [1, 1]},
								"up": {"uv": [0, 4], "uv_size": [1, 1]},
								"down": {"uv": [4, 1], "uv_size": [1, -1]}
							}
						},
						{
							"origin": [-0.73367, 0.13206, -0.75],
							"size": [0.9, 0.8, 0.3],
							"uv": {
								"north": {"uv": [2, 4], "uv_size": [1, 1]},
								"east": {"uv": [4, 2], "uv_size": [1, 1]},
								"south": {"uv": [4, 4], "uv_size": [1, 1]},
								"west": {"uv": [0, 6], "uv_size": [1, 1]},
								"up": {"uv": [6, 0], "uv_size": [1, 1]},
								"down": {"uv": [2, 7], "uv_size": [1, -1]}
							}
						},
						{
							"origin": [0.06633, 1.83206, -0.35],
							"size": [0.2, 0.4, 0.3],
							"pivot": [0.16633, 1.83206, -0.2],
							"rotation": [0, 0, -21],
							"uv": {
								"north": {"uv": [6, 2], "uv_size": [1, 1]},
								"east": {"uv": [4, 6], "uv_size": [1, 1]},
								"south": {"uv": [6, 4], "uv_size": [1, 1]},
								"west": {"uv": [6, 6], "uv_size": [1, 1]},
								"up": {"uv": [0, 8], "uv_size": [1, 1]},
								"down": {"uv": [8, 1], "uv_size": [1, -1]}
							}
						},
						{
							"origin": [-0.33367, 2.03206, -0.35],
							"size": [0.2, 0.4, 0.3],
							"pivot": [0.16633, 1.83206, -0.2],
							"rotation": [0, 0, -21],
							"uv": {
								"north": {"uv": [2, 8], "uv_size": [1, 1]},
								"east": {"uv": [8, 2], "uv_size": [1, 1]},
								"south": {"uv": [4, 8], "uv_size": [1, 1]},
								"west": {"uv": [8, 4], "uv_size": [1, 1]},
								"up": {"uv": [6, 8], "uv_size": [1, 1]},
								"down": {"uv": [8, 7], "uv_size": [1, -1]}
							}
						},
						{
							"origin": [-0.53367, 2.13206, -0.35],
							"size": [0.2, 0.3, 0.3],
							"pivot": [0.16633, 1.83206, -0.2],
							"rotation": [0, 0, -21],
							"uv": {
								"north": {"uv": [8, 8], "uv_size": [1, 1]},
								"east": {"uv": [0, 10], "uv_size": [1, 1]},
								"south": {"uv": [10, 0], "uv_size": [1, 1]},
								"west": {"uv": [2, 10], "uv_size": [1, 1]},
								"up": {"uv": [10, 2], "uv_size": [1, 1]},
								"down": {"uv": [4, 11], "uv_size": [1, -1]}
							}
						},
						{
							"origin": [-0.04118, 2.35198, -0.35],
							"size": [0.2, 0.4, 0.3],
							"pivot": [0.16633, 2.13206, -0.2],
							"rotation": [0, 0, -77],
							"uv": {
								"north": {"uv": [10, 4], "uv_size": [1, 1]},
								"east": {"uv": [6, 10], "uv_size": [1, 1]},
								"south": {"uv": [10, 6], "uv_size": [1, 1]},
								"west": {"uv": [8, 10], "uv_size": [1, 1]},
								"up": {"uv": [10, 8], "uv_size": [1, 1]},
								"down": {"uv": [10, 11], "uv_size": [1, -1]}
							}
						},
						{
							"origin": [0.05882, 2.25198, -0.35],
							"size": [0.2, 0.4, 0.3],
							"pivot": [0.16633, 2.13206, -0.2],
							"rotation": [0, 0, -77],
							"uv": {
								"north": {"uv": [0, 12], "uv_size": [1, 1]},
								"east": {"uv": [12, 0], "uv_size": [1, 1]},
								"south": {"uv": [2, 12], "uv_size": [1, 1]},
								"west": {"uv": [12, 2], "uv_size": [1, 1]},
								"up": {"uv": [4, 12], "uv_size": [1, 1]},
								"down": {"uv": [12, 5], "uv_size": [1, -1]}
							}
						},
						{
							"origin": [0.06633, 1.43206, -0.35],
							"size": [0.2, 0.4, 0.3],
							"uv": {
								"north": {"uv": [6, 12], "uv_size": [1, 1]},
								"east": {"uv": [12, 6], "uv_size": [1, 1]},
								"south": {"uv": [8, 12], "uv_size": [1, 1]},
								"west": {"uv": [12, 8], "uv_size": [1, 1]},
								"up": {"uv": [10, 12], "uv_size": [1, 1]},
								"down": {"uv": [12, 11], "uv_size": [1, -1]}
							}
						},
						{
							"origin": [-0.03367, 1.03206, -0.35],
							"size": [0.2, 0.4, 0.3],
							"uv": {
								"north": {"uv": [12, 12], "uv_size": [1, 1]},
								"east": {"uv": [0, 14], "uv_size": [1, 1]},
								"south": {"uv": [14, 0], "uv_size": [1, 1]},
								"west": {"uv": [2, 14], "uv_size": [1, 1]},
								"up": {"uv": [14, 2], "uv_size": [1, 1]},
								"down": {"uv": [4, 15], "uv_size": [1, -1]}
							}
						}
					]
				},
				{
					"name": "peel2",
					"parent": "leaf",
					"pivot": [0.625, 2.025, -0.35],
					"cubes": [
						{
							"origin": [0.46633, 0.13206, -0.75],
							"size": [0.8, 0.8, 0.3],
							"uv": {
								"north": {"uv": [14, 4], "uv_size": [1, 1]},
								"east": {"uv": [6, 14], "uv_size": [1, 1]},
								"south": {"uv": [14, 6], "uv_size": [1, 1]},
								"west": {"uv": [8, 14], "uv_size": [1, 1]},
								"up": {"uv": [14, 8], "uv_size": [1, 1]},
								"down": {"uv": [10, 15], "uv_size": [1, -1]}
							}
						},
						{
							"origin": [0.36633, 0.03206, -0.65],
							"size": [1, 1, 1],
							"uv": {
								"north": {"uv": [14, 10], "uv_size": [1, 1]},
								"east": {"uv": [12, 14], "uv_size": [1, 1]},
								"south": {"uv": [14, 12], "uv_size": [1, 1]},
								"west": {"uv": [14, 14], "uv_size": [1, 1]},
								"up": {"uv": [0, 16], "uv_size": [1, 1]},
								"down": {"uv": [16, 1], "uv_size": [1, -1]}
							}
						},
						{
							"origin": [0.86633, 1.03206, -0.35],
							"size": [0.2, 0.4, 0.3],
							"uv": {
								"north": {"uv": [2, 16], "uv_size": [1, 1]},
								"east": {"uv": [16, 2], "uv_size": [1, 1]},
								"south": {"uv": [4, 16], "uv_size": [1, 1]},
								"west": {"uv": [16, 4], "uv_size": [1, 1]},
								"up": {"uv": [6, 16], "uv_size": [1, 1]},
								"down": {"uv": [16, 7], "uv_size": [1, -1]}
							}
						},
						{
							"origin": [0.96633, 1.43206, -0.35],
							"size": [0.2, 0.4, 0.3],
							"uv": {
								"north": {"uv": [8, 16], "uv_size": [1, 1]},
								"east": {"uv": [16, 8], "uv_size": [1, 1]},
								"south": {"uv": [10, 16], "uv_size": [1, 1]},
								"west": {"uv": [16, 10], "uv_size": [1, 1]},
								"up": {"uv": [12, 16], "uv_size": [1, 1]},
								"down": {"uv": [16, 13], "uv_size": [1, -1]}
							}
						},
						{
							"origin": [1.05882, 2.35198, -0.35],
							"size": [0.2, 0.4, 0.3],
							"pivot": [1.16633, 2.13206, -0.2],
							"rotation": [0, 0, -77],
							"uv": {
								"north": {"uv": [14, 16], "uv_size": [1, 1]},
								"east": {"uv": [16, 14], "uv_size": [1, 1]},
								"south": {"uv": [16, 16], "uv_size": [1, 1]},
								"west": {"uv": [0, 18], "uv_size": [1, 1]},
								"up": {"uv": [18, 0], "uv_size": [1, 1]},
								"down": {"uv": [2, 19], "uv_size": [1, -1]}
							}
						},
						{
							"origin": [0.95882, 2.45198, -0.35],
							"size": [0.2, 0.4, 0.3],
							"pivot": [1.16633, 2.13206, -0.2],
							"rotation": [0, 0, -77],
							"uv": {
								"north": {"uv": [18, 2], "uv_size": [1, 1]},
								"east": {"uv": [4, 18], "uv_size": [1, 1]},
								"south": {"uv": [18, 4], "uv_size": [1, 1]},
								"west": {"uv": [6, 18], "uv_size": [1, 1]},
								"up": {"uv": [18, 6], "uv_size": [1, 1]},
								"down": {"uv": [8, 19], "uv_size": [1, -1]}
							}
						},
						{
							"origin": [0.85882, 2.65198, -0.35],
							"size": [0.2, 0.4, 0.3],
							"pivot": [1.16633, 2.13206, -0.2],
							"rotation": [0, 0, -77],
							"uv": {
								"north": {"uv": [18, 8], "uv_size": [1, 1]},
								"east": {"uv": [10, 18], "uv_size": [1, 1]},
								"south": {"uv": [18, 10], "uv_size": [1, 1]},
								"west": {"uv": [12, 18], "uv_size": [1, 1]},
								"up": {"uv": [18, 12], "uv_size": [1, 1]},
								"down": {"uv": [14, 19], "uv_size": [1, -1]}
							}
						},
						{
							"origin": [0.96633, 1.83206, -0.35],
							"size": [0.2, 0.4, 0.3],
							"pivot": [1.16633, 1.83206, -0.2],
							"rotation": [0, 0, -21],
							"uv": {
								"north": {"uv": [18, 14], "uv_size": [1, 1]},
								"east": {"uv": [16, 18], "uv_size": [1, 1]},
								"south": {"uv": [18, 16], "uv_size": [1, 1]},
								"west": {"uv": [18, 18], "uv_size": [1, 1]},
								"up": {"uv": [0, 20], "uv_size": [1, 1]},
								"down": {"uv": [20, 1], "uv_size": [1, -1]}
							}
						}
					]
				}
			]
		}
	]
}